mrtoolstheme/__init__.py
mrtoolstheme/layout.html
mrtoolstheme/support.py
mrtoolstheme/theme.conf
mrtoolstheme/static/mrtools.css_t
mrtoolstheme-0.5.1.dist-info/LICENSE
mrtoolstheme-0.5.1.dist-info/METADATA
mrtoolstheme-0.5.1.dist-info/WHEEL
mrtoolstheme-0.5.1.dist-info/entry_points.txt
mrtoolstheme-0.5.1.dist-info/top_level.txt
mrtoolstheme-0.5.1.dist-info/RECORD
