Metadata-Version: 2.1
Name: mrtoolstheme
Version: 0.5.1
Summary: mrtoolstheme: a Sphinx theme
Home-page: https://gitlab.com/anatas_ch/pyl_mrtoolstheme
Author: Michael Rippstein
Author-email: info@anatas.ch
License: AGPL-3.0
Project-URL: Documentation, https://mrtoolstheme.readthedocs.io/
Project-URL: Bug Tracker, https://gitlab.com/anatas_ch/pyl_mrtoolstheme/-/issues
Project-URL: Source Code, https://gitlab.com/anatas_ch/pyl_mrtoolstheme
Keywords: syntax highlighting,sphinx doc theme
Classifier: Development Status :: 3 - Alpha
Classifier: Intended Audience :: Developers
Classifier: Intended Audience :: End Users/Desktop
Classifier: Intended Audience :: System Administrators
Classifier: License :: OSI Approved :: GNU Affero General Public License v3 or later (AGPLv3+)
Classifier: Operating System :: OS Independent
Classifier: Environment :: Console
Classifier: Environment :: Web Environment
Classifier: Programming Language :: Python
Classifier: Programming Language :: Python :: 3
Classifier: Programming Language :: Python :: 3.9
Classifier: Programming Language :: Python :: 3.10
Classifier: Programming Language :: Python :: 3.11
Classifier: Programming Language :: Python :: Implementation :: CPython
Classifier: Programming Language :: Python :: Implementation :: PyPy
Classifier: Framework :: Sphinx :: Theme
Classifier: Topic :: Documentation
Classifier: Topic :: Documentation :: Sphinx
Classifier: Topic :: Software Development :: Documentation
Classifier: Topic :: Text Processing :: Filters
Classifier: Topic :: Utilities
Requires-Python: >=3.9
License-File: LICENSE
Requires-Dist: Sphinx (>=6.1.3)
Requires-Dist: docutils (>=0.19)
